tcolor/__init__.py
tcolor_livereboot-0.0.2.dist-info/LICENCE
tcolor_livereboot-0.0.2.dist-info/METADATA
tcolor_livereboot-0.0.2.dist-info/WHEEL
tcolor_livereboot-0.0.2.dist-info/top_level.txt
tcolor_livereboot-0.0.2.dist-info/RECORD
