Metadata-Version: 2.1
Name: tcolor-livereboot
Version: 0.0.2
Summary: A package to add colors in your terminal.
Home-page: https://github.com/LiveReboot/TerminalDisplay
Author: LiveReboot
Author-email: contact@livereboot.fr
License: UNKNOWN
Project-URL: Bug Tracker, https://github.com/LiveReboot/TerminalDisplay/issues
Platform: UNKNOWN
Classifier: Programming Language :: Python :: 3
Classifier: License :: OSI Approved :: MIT License
Classifier: Operating System :: OS Independent
Requires-Python: >=3.6
License-File: LICENCE
